obsout/__main__.py
obsout/config.py
obsout/console.py
obsout/outline/__init__.py
obsout/outline/artifacts.py
obsout/outline/client.py
obsout/outline/constants.py
obsout/outline/outline.py
obsout/outline/utils.py
obsout-0.1.3.dist-info/LICENSE.md
obsout-0.1.3.dist-info/METADATA
obsout-0.1.3.dist-info/WHEEL
obsout-0.1.3.dist-info/entry_points.txt
obsout-0.1.3.dist-info/RECORD
